{
    "license": "CC0-1.0",
    "description": {
        "eu": "Datu meteorologikoak"
    },
    "schema": {
        "fields": [
            {
                "name": "date",
                "type": "string",
                "title": {
                    "ar": "data"
                }
            },
            {
                "name": "avgTemp",
                "type": "number",
                "title": {
                    "eu": "Batazbesteko tenperatura"
                }
            },
            {
                "name": "highTemp",
                "type": "number",
                "title": {
                    "eu": "Tenperatura maximoa"
                }
            },
            {
                "name": "highTempAvg",
                "type": "number",
                "title": {
                    "eu": "Tenperatura maximoaren batezbestekoa"
                }
            },
            {
                "name": "lowTemp",
                "type": "number",
                "title": {
                    "eu": "Tenperatura minimoa"
                }
            },
            {
                "name": "lowTempAvg",
                "type": "number",
                "title": {
                    "eu": "Tenperatura minimoaren batezbestekoa"
                }
            },
            {
                "name": "hez",
                "type": "number",
                "title": {
                    "eu": "Batazbesteko hezetasuna"
                }
            },
            {
                "name": "precip",
                "type": "number",
                "title": {
                    "eu": "Pilatutako prezipitazioak"
                }
            }
        ]
    },
    "data": [
        [
            "01/2000",
            -1.6409374999999997,
            16.68,
            8.810312500000002,
            -0.99,
            3.1503125000000005,
            77.45531249999999,
            90.64062499999997
        ],
        [
            "02/2000",
            1.793793103448276,
            21.18,
            15.529310344827586,
            4.17,
            8.722413793103447,
            66.97275862068966,
            87.3344827586207
        ],
        [
            "03/2000",
            2.9190322580645165,
            25.12,
            17.148064516129033,
            4.69,
            9.642580645161287,
            63.04290322580646,
            84.90000000000002
        ],
        [
            "04/2000",
            6.450666666666667,
            25.58,
            17.009333333333334,
            7.02,
            11.721666666666666,
            69.02666666666667,
            90.72666666666669
        ],
        [
            "05/2000",
            11.334193548387097,
            31.62,
            24.456451612903226,
            13.89,
            17.668387096774193,
            62.625161290322566,
            86.52903225806453
        ],
        [
            "06/2000",
            14.434333333333331,
            35.85,
            27.673000000000002,
            12.71,
            20.954666666666665,
            57.71799999999999,
            81.53533333333336
        ],
        [
            "07/2000",
            14.916129032258066,
            35.79,
            28.4074193548387,
            15.24,
            21.46741935483871,
            59.22161290322581,
            84.52290322580647
        ],
        [
            "08/2000",
            14.740967741935483,
            35.21,
            29.493548387096773,
            17.08,
            21.829032258064515,
            61.43645161290322,
            88.48387096774195
        ],
        [
            "09/2000",
            11.903999999999998,
            33.67,
            26.027666666666676,
            12.33,
            18.544333333333334,
            66.35566666666665,
            89.03333333333335
        ],
        [
            "10/2000",
            8.63967741935484,
            26.52,
            18.83096774193549,
            9.22,
            13.357741935483872,
            74.35516129032258,
            90.49999999999999
        ],
        [
            "11/2000",
            3.7713333333333328,
            19.22,
            13.177999999999999,
            3.85,
            8.433,
            79.98566666666666,
            93.05333333333334
        ],
        [
            "12/2000",
            5.73,
            12.14,
            12.14,
            8.88,
            8.88,
            69.24,
            79.5
        ],
        [
            "01/2001",
            3.272258064516129,
            18.54,
            11.272258064516128,
            2.71,
            7.283548387096773,
            78.4293548387097,
            91.13870967741933
        ],
        [
            "02/2001",
            1.4707142857142854,
            18.08,
            12.948928571428572,
            3.27,
            6.784285714285716,
            71.43107142857143,
            89.13571428571429
        ],
        [
            "03/2001",
            7.259677419354839,
            27.65,
            18.54096774193548,
            8.48,
            12.897419354838712,
            70.77129032258063,
            88.49419354838709
        ],
        [
            "04/2001",
            5.486666666666666,
            24.29,
            17.581333333333337,
            5.94,
            11.387333333333334,
            63.125,
            84.43033333333332
        ],
        [
            "05/2001",
            9.813870967741936,
            35.82,
            24.095161290322583,
            8.97,
            16.855483870967742,
            60.748709677419356,
            84.98645161290322
        ],
        [
            "06/2001",
            12.685333333333334,
            38.9,
            29.555666666666664,
            14.68,
            21.17,
            51.734333333333325,
            81.17733333333332
        ],
        [
            "07/2001",
            14.07,
            36.76,
            29.664516129032254,
            16.01,
            21.60935483870968,
            59.20290322580645,
            87.01096774193549
        ],
        [
            "08/2001",
            15.53,
            36.49,
            30.224193548387092,
            16.95,
            22.43645161290323,
            59.519354838709674,
            85.31516129032258
        ],
        [
            "09/2001",
            10.778666666666668,
            29.26,
            23.787666666666674,
            13.01,
            16.980999999999995,
            65.52566666666667,
            86.57333333333334
        ],
        [
            "10/2001",
            9.238064516129034,
            27.21,
            22.467419354838718,
            10.48,
            15.69935483870968,
            72.07032258064515,
            91.95483870967742
        ],
        [
            "11/2001",
            2.6279999999999997,
            18.6,
            12.346666666666668,
            2.92,
            7.171666666666666,
            72.85533333333335,
            87.18633333333331
        ],
        [
            "12/2001",
            3.5,
            6.25,
            6.25,
            4.99,
            4.99,
            85.86,
            91.8
        ],
        [
            "01/2002",
            1.4854838709677423,
            17.53,
            11.511612903225805,
            2.28,
            6.054516129032259,
            80.49935483870968,
            91.99032258064517
        ],
        [
            "02/2002",
            2.885357142857143,
            18.17,
            13.532142857142858,
            4.39,
            7.841428571428572,
            73.20821428571428,
            88.52500000000002
        ],
        [
            "03/2002",
            5.719032258064516,
            26.27,
            17.41354838709677,
            5.58,
            11.281612903225808,
            63.104193548387094,
            83.02741935483873
        ],
        [
            "04/2002",
            6.255666666666666,
            27.09,
            18.614333333333335,
            5.04,
            12.403000000000002,
            59.400666666666666,
            81.866
        ],
        [
            "05/2002",
            8.753548387096773,
            31.39,
            21.720322580645163,
            9.36,
            15.353548387096772,
            60.33774193548386,
            85.288064516129
        ],
        [
            "06/2002",
            13.959333333333335,
            37.42,
            28.07933333333334,
            12.57,
            20.806,
            54.79266666666669,
            78.092
        ],
        [
            "07/2002",
            14.181612903225805,
            35.68,
            27.706774193548384,
            16.78,
            20.662258064516124,
            59.23064516129032,
            81.56935483870969
        ],
        [
            "08/2002",
            14.311290322580644,
            34.21,
            26.97096774193549,
            15.62,
            20.267096774193543,
            64.81903225806451,
            86.89903225806451
        ],
        [
            "09/2002",
            11.621,
            29.21,
            24.751999999999995,
            12.89,
            17.63266666666667,
            67.93733333333334,
            89.91333333333333
        ],
        [
            "10/2002",
            7.949032258064515,
            25.48,
            20.41516129032258,
            7.91,
            14.077419354838709,
            76.96032258064515,
            94.30967741935483
        ],
        [
            "11/2002",
            5.261666666666668,
            21.47,
            15.486333333333334,
            7.2,
            10.329333333333334,
            78.4086666666667,
            93.00666666666666
        ],
        [
            "12/2002",
            3.91,
            13.76,
            13.76,
            9.08,
            9.08,
            89.64,
            96.0
        ],
        [
            "01/2003",
            1.1493548387096775,
            18.27,
            9.643870967741934,
            -0.71,
            5.2235483870967725,
            77.66451612903225,
            90.71322580645163
        ],
        [
            "02/2003",
            1.5971428571428572,
            15.79,
            10.069642857142858,
            -0.15,
            5.6792857142857125,
            78.23392857142858,
            91.42142857142856
        ],
        [
            "03/2003",
            4.199677419354838,
            21.78,
            17.757741935483875,
            7.17,
            10.790322580645162,
            71.49774193548386,
            91.76774193548388
        ],
        [
            "04/2003",
            6.7,
            26.07,
            18.85766666666667,
            7.56,
            12.947,
            67.955,
            88.66666666666669
        ],
        [
            "05/2003",
            9.46225806451613,
            33.18,
            23.615483870967743,
            9.95,
            16.59935483870968,
            62.89645161290323,
            87.60967741935484
        ],
        [
            "06/2003",
            17.029999999999998,
            37.28,
            31.691333333333326,
            19.19,
            24.123666666666672,
            57.910666666666664,
            86.408
        ],
        [
            "07/2003",
            15.887419354838704,
            36.81,
            31.804516129032258,
            19.0,
            23.528709677419354,
            58.52548387096774,
            86.16451612903226
        ],
        [
            "08/2003",
            16.65967741935484,
            38.42,
            32.94193548387098,
            18.0,
            24.156451612903226,
            64.90322580645162,
            92.3225806451613
        ],
        [
            "09/2003",
            12.622000000000003,
            30.23,
            25.033333333333324,
            14.69,
            18.399,
            73.78366666666668,
            93.19666666666667
        ],
        [
            "10/2003",
            8.327741935483871,
            24.64,
            17.91548387096774,
            6.3,
            12.868387096774196,
            79.82032258064517,
            93.64838709677417
        ],
        [
            "11/2003",
            4.1066666666666665,
            18.99,
            14.701333333333332,
            5.12,
            8.952666666666666,
            85.48800000000001,
            95.17666666666668
        ],
        [
            "12/2003",
            -0.49,
            8.36,
            8.36,
            3.99,
            3.99,
            84.34,
            93.1
        ],
        [
            "01/2004",
            2.6816129032258065,
            17.71,
            11.721290322580648,
            0.69,
            6.745806451612904,
            83.33774193548388,
            92.75161290322578
        ],
        [
            "02/2004",
            0.6762068965517244,
            15.84,
            9.15655172413793,
            -0.07,
            4.572068965517243,
            83.1396551724138,
            93.98275862068964
        ],
        [
            "03/2004",
            2.4648387096774194,
            21.38,
            13.555806451612904,
            1.85,
            7.7712903225806444,
            76.16129032258065,
            92.44516129032256
        ],
        [
            "04/2004",
            4.869000000000001,
            24.14,
            16.558333333333337,
            6.27,
            10.679333333333336,
            72.376,
            90.32333333333331
        ],
        [
            "05/2004",
            8.603225806451615,
            29.03,
            22.16096774193549,
            8.69,
            15.355806451612903,
            68.05774193548388,
            90.66451612903226
        ],
        [
            "06/2004",
            14.709000000000001,
            37.08,
            29.33966666666667,
            16.14,
            22.05466666666667,
            57.14133333333335,
            82.15433333333334
        ],
        [
            "07/2004",
            14.828387096774192,
            36.42,
            29.277419354838703,
            15.91,
            21.824193548387093,
            62.39064516129032,
            88.6
        ],
        [
            "08/2004",
            14.967096774193545,
            35.87,
            29.64709677419355,
            18.1,
            21.77193548387097,
            65.41129032258064,
            90.98064516129031
        ],
        [
            "09/2004",
            13.293999999999995,
            34.01,
            26.61766666666667,
            14.86,
            19.216666666666665,
            69.48266666666667,
            89.66666666666669
        ],
        [
            "10/2004",
            9.79,
            30.11,
            21.61193548387097,
            9.55,
            15.464516129032257,
            71.25064516129032,
            90.51290322580644
        ],
        [
            "11/2004",
            2.661,
            17.51,
            11.819000000000004,
            2.72,
            7.022666666666668,
            79.79999999999998,
            90.03999999999999
        ],
        [
            "12/2004",
            6.03,
            15.02,
            15.02,
            9.54,
            9.54,
            75.2,
            87.3
        ],
        [
            "01/2005",
            0.6319354838709679,
            15.02,
            7.061612903225807,
            -1.79,
            3.577741935483871,
            81.36064516129034,
            90.54354838709678
        ],
        [
            "02/2005",
            -2.1025,
            16.7,
            8.832857142857142,
            -2.59,
            3.075714285714285,
            71.58964285714283,
            87.50714285714285
        ],
        [
            "03/2005",
            1.6493548387096773,
            24.88,
            17.03870967741935,
            1.14,
            9.270322580645162,
            61.716451612903235,
            85.60483870967741
        ],
        [
            "04/2005",
            6.087000000000001,
            30.65,
            18.801333333333336,
            4.07,
            12.462333333333333,
            68.42266666666669,
            88.33566666666667
        ],
        [
            "05/2005",
            9.768387096774193,
            32.13,
            24.021612903225805,
            12.0,
            16.896129032258063,
            62.66096774193548,
            86.65870967741935
        ],
        [
            "06/2005",
            15.130333333333336,
            35.96,
            30.28066666666667,
            17.56,
            22.520333333333333,
            57.043000000000006,
            84.79566666666668
        ],
        [
            "07/2005",
            14.908064516129032,
            38.71,
            30.12548387096775,
            17.67,
            22.459677419354843,
            57.570967741935476,
            85.01290322580645
        ],
        [
            "08/2005",
            14.588709677419354,
            32.52,
            28.38806451612903,
            15.52,
            21.33129032258065,
            61.52516129032257,
            85.1741935483871
        ],
        [
            "09/2005",
            11.440000000000001,
            34.54,
            25.20466666666666,
            13.1,
            18.086333333333336,
            64.13066666666664,
            87.43533333333333
        ],
        [
            "10/2005",
            9.770322580645162,
            25.49,
            20.45741935483871,
            11.56,
            14.95838709677419,
            76.15451612903226,
            90.99032258064517
        ],
        [
            "11/2005",
            2.590333333333333,
            19.46,
            12.560000000000002,
            2.09,
            7.608333333333333,
            80.47633333333334,
            92.82333333333331
        ],
        [
            "12/2005",
            1.75,
            9.54,
            9.54,
            5.79,
            5.79,
            80.8,
            93.1
        ],
        [
            "01/2006",
            0.49483870967741933,
            14.69,
            9.087096774193549,
            -1.55,
            4.700322580645159,
            82.6609677419355,
            93.63225806451611
        ],
        [
            "02/2006",
            -1.356785714285714,
            19.52,
            11.685714285714287,
            0.93,
            5.099285714285714,
            69.62392857142858,
            88.45357142857142
        ],
        [
            "03/2006",
            5.115483870967743,
            23.7,
            17.39161290322581,
            3.77,
            11.144193548387097,
            70.27709677419357,
            89.63193548387096
        ],
        [
            "04/2006",
            5.933666666666666,
            23.48,
            19.38666666666667,
            7.26,
            12.674,
            68.62599999999999,
            89.94666666666666
        ],
        [
            "05/2006",
            10.063870967741934,
            33.06,
            24.488709677419358,
            12.02,
            17.19612903225806,
            64.13451612903226,
            88.38387096774194
        ],
        [
            "06/2006",
            14.172333333333333,
            36.02,
            29.722666666666658,
            15.46,
            21.63,
            57.77433333333333,
            83.22566666666667
        ],
        [
            "07/2006",
            16.87548387096774,
            38.29,
            32.46677419354838,
            19.05,
            24.274193548387096,
            61.368387096774185,
            88.3935483870968
        ],
        [
            "08/2006",
            13.235483870967741,
            32.66,
            26.904516129032256,
            17.33,
            19.93903225806451,
            61.97580645161291,
            85.93548387096774
        ],
        [
            "09/2006",
            13.154333333333334,
            36.41,
            27.012,
            14.62,
            19.522,
            70.84500000000001,
            91.96000000000001
        ],
        [
            "10/2006",
            10.5,
            27.65,
            22.495806451612907,
            13.14,
            16.26258064516129,
            75.37741935483872,
            92.4258064516129
        ],
        [
            "11/2006",
            6.045000000000001,
            19.76,
            16.46633333333334,
            4.12,
            11.123,
            79.815,
            93.02666666666666
        ],
        [
            "12/2006",
            "null",
            "null",
            "null",
            "null",
            "null",
            "null",
            "null"
        ],
        [
            "01/2007",
            -0.3403225806451613,
            17.98,
            5.800645161290323,
            -3.28,
            1.2493548387096773,
            75.05935483870967,
            79.78064516129032
        ],
        [
            "02/2007",
            2.880357142857142,
            18.74,
            14.295714285714292,
            1.18,
            8.424642857142857,
            84.54035714285715,
            99.27857142857142
        ],
        [
            "03/2007",
            3.157741935483872,
            22.28,
            13.883870967741936,
            0.8,
            8.268709677419354,
            80.1625806451613,
            97.03870967741936
        ],
        [
            "04/2007",
            7.287000000000002,
            28.44,
            20.056666666666672,
            6.04,
            13.290666666666663,
            80.58099999999999,
            99.47
        ],
        [
            "05/2007",
            9.78741935483871,
            30.24,
            22.676129032258064,
            11.03,
            16.23741935483871,
            70.80709677419354,
            94.44838709677417
        ],
        [
            "06/2007",
            12.562,
            35.07,
            27.649666666666665,
            15.51,
            20.14,
            64.71866666666668,
            94.13333333333331
        ],
        [
            "07/2007",
            12.675161290322583,
            36.28,
            27.417419354838703,
            "null",
            20.09387096774194,
            56.85387096774192,
            84.20967741935483
        ],
        [
            "08/2007",
            13.379677419354836,
            37.28,
            27.557741935483865,
            15.37,
            20.2958064516129,
            65.87774193548387,
            93.26774193548384
        ],
        [
            "09/2007",
            11.008000000000003,
            30.37,
            24.92566666666666,
            11.26,
            17.7,
            71.35533333333332,
            95.41333333333334
        ],
        [
            "10/2007",
            8.175161290322581,
            25.36,
            19.896451612903228,
            7.79,
            13.42967741935484,
            76.67967741935483,
            94.9516129032258
        ],
        [
            "11/2007",
            2.469,
            20.53,
            14.151000000000005,
            0.7,
            8.035999999999998,
            69.05666666666667,
            88.67566666666669
        ],
        [
            "12/2007",
            -6.89,
            6.2,
            6.2,
            -2.05,
            -2.05,
            94.41,
            100.0
        ],
        [
            "01/2008",
            0.09935483870967733,
            18.72,
            12.14064516129032,
            -0.66,
            5.880322580645162,
            87.51645161290324,
            99.46774193548387
        ],
        [
            "02/2008",
            1.8368965517241378,
            20.25,
            14.654827586206897,
            3.28,
            7.885862068965516,
            82.19724137931037,
            98.40689655172415
        ],
        [
            "03/2008",
            2.798709677419355,
            23.75,
            13.885806451612902,
            "null",
            8.378064516129031,
            72.5951612903226,
            91.77387096774193
        ],
        [
            "04/2008",
            5.936999999999999,
            29.25,
            19.10066666666667,
            7.84,
            12.543000000000001,
            68.50099999999999,
            93.07666666666665
        ],
        [
            "05/2008",
            10.257096774193547,
            27.7,
            21.048709677419353,
            12.11,
            15.417419354838712,
            77.7925806451613,
            96.81935483870967
        ],
        [
            "06/2008",
            13.082333333333333,
            34.72,
            26.064999999999998,
            13.22,
            19.27333333333333,
            68.78833333333334,
            92.47300000000001
        ],
        [
            "07/2008",
            13.819354838709678,
            35.81,
            28.992258064516125,
            15.36,
            21.39870967741935,
            65.55709677419355,
            93.8451612903226
        ],
        [
            "08/2008",
            13.752258064516129,
            36.15,
            29.399032258064516,
            15.86,
            21.251612903225805,
            68.6906451612903,
            96.69032258064514
        ],
        [
            "09/2008",
            8.501000000000001,
            32.12,
            22.087333333333337,
            "null",
            15.585666666666668,
            63.33400000000002,
            86.33
        ],
        [
            "10/2008",
            6.500645161290322,
            25.55,
            19.148064516129025,
            5.58,
            12.251612903225805,
            82.70387096774193,
            99.15483870967742
        ],
        [
            "11/2008",
            2.9113333333333338,
            16.46,
            11.65633333333333,
            -0.58,
            7.104333333333331,
            80.857,
            92.67333333333335
        ],
        [
            "12/2008",
            1.08,
            12.02,
            12.02,
            6.83,
            6.83,
            95.8,
            100.0
        ],
        [
            "01/2009",
            -0.6206451612903228,
            17.34,
            8.816774193548389,
            -1.14,
            3.868064516129033,
            89.22806451612902,
            99.04838709677419
        ],
        [
            "02/2009",
            1.1624999999999999,
            15.97,
            12.125357142857144,
            2.76,
            6.3875,
            76.99321428571429,
            94.0607142857143
        ],
        [
            "03/2009",
            2.3693548387096777,
            23.82,
            16.372258064516124,
            2.97,
            9.36451612903226,
            67.53612903225806,
            91.1774193548387
        ],
        [
            "04/2009",
            4.748666666666667,
            26.77,
            17.073333333333334,
            6.94,
            11.03333333333333,
            73.61166666666666,
            95.63000000000002
        ],
        [
            "05/2009",
            10.650322580645161,
            31.73,
            25.12516129032258,
            11.74,
            17.791612903225808,
            66.65451612903227,
            93.66774193548386
        ],
        [
            "06/2009",
            14.158666666666667,
            37.9,
            29.313666666666666,
            16.25,
            21.698666666666664,
            62.54766666666667,
            91.92333333333335
        ],
        [
            "07/2009",
            14.774516129032259,
            37.03,
            30.96290322580645,
            18.36,
            22.625483870967738,
            61.761935483870964,
            92.21935483870966
        ],
        [
            "08/2009",
            15.44483870967742,
            37.84,
            31.591612903225805,
            18.56,
            22.998387096774188,
            65.9783870967742,
            93.20645161290324
        ],
        [
            "09/2009",
            11.376666666666669,
            31.38,
            26.094333333333335,
            13.33,
            18.076666666666668,
            73.49633333333334,
            97.06999999999998
        ],
        [
            "10/2009",
            9.103870967741937,
            30.86,
            22.529677419354837,
            8.78,
            15.271935483870967,
            71.43387096774192,
            91.76903225806451
        ],
        [
            "11/2009",
            4.36,
            20.87,
            14.925333333333334,
            4.72,
            9.643,
            84.00333333333333,
            98.03333333333333
        ],
        [
            "12/2009",
            -0.88,
            9.74,
            9.74,
            5.31,
            5.31,
            80.1,
            100.0
        ],
        [
            "01/2010",
            -0.27677419354838695,
            13.36,
            6.964193548387097,
            -1.31,
            3.262258064516129,
            85.24548387096776,
            94.95161290322581
        ],
        [
            "02/2010",
            0.8071428571428569,
            18.5,
            10.042857142857143,
            -0.99,
            5.531071428571431,
            79.3425,
            94.89642857142857
        ],
        [
            "03/2010",
            2.6632258064516123,
            21.7,
            14.282903225806448,
            0.58,
            8.347741935483871,
            70.30709677419354,
            93.14774193548386
        ],
        [
            "04/2010",
            6.335999999999999,
            28.58,
            20.068666666666665,
            8.11,
            13.196666666666669,
            69.70266666666667,
            96.87333333333332
        ],
        [
            "05/2010",
            8.022903225806452,
            29.59,
            21.07032258064516,
            6.86,
            14.669999999999998,
            66.06838709677419,
            93.49354838709678
        ],
        [
            "06/2010",
            12.503999999999998,
            35.41,
            26.230999999999995,
            13.19,
            19.273333333333337,
            66.19,
            94.85333333333332
        ],
        [
            "07/2010",
            15.617741935483869,
            38.16,
            30.77516129032258,
            17.97,
            22.98225806451613,
            63.759354838709676,
            92.99354838709678
        ],
        [
            "08/2010",
            14.001935483870966,
            38.1,
            28.88290322580646,
            16.92,
            21.28580645161291,
            66.31774193548388,
            95.14838709677419
        ],
        [
            "09/2010",
            10.809666666666663,
            33.6,
            25.595666666666666,
            12.5,
            17.99366666666667,
            68.86800000000002,
            96.87333333333335
        ],
        [
            "10/2010",
            7.506451612903224,
            27.58,
            19.34193548387097,
            8.23,
            13.046774193548384,
            73.61290322580646,
            94.53870967741936
        ],
        [
            "11/2010",
            1.9383333333333328,
            22.54,
            12.701333333333336,
            -1.6,
            6.973333333333333,
            87.12333333333332,
            96.3
        ],
        [
            "12/2010",
            3.43,
            13.56,
            13.56,
            7.87,
            7.87,
            87.5,
            100.0
        ],
        [
            "01/2011",
            0.450967741935484,
            16.05,
            7.655483870967741,
            -0.23,
            3.9499999999999993,
            62.49806451612904,
            48.73870967741936
        ],
        [
            "02/2011",
            1.3892857142857142,
            18.6,
            10.119285714285713,
            "null",
            5.440357142857144,
            63.78821428571429,
            76.63928571428572
        ],
        [
            "03/2011",
            3.8241935483870964,
            25.03,
            15.048387096774198,
            3.15,
            9.374516129032259,
            80.34838709677419,
            97.06451612903228
        ],
        [
            "04/2011",
            8.216000000000001,
            30.21,
            21.41433333333334,
            11.72,
            14.564999999999998,
            71.47466666666669,
            93.62999999999998
        ],
        [
            "05/2011",
            9.884838709677421,
            32.77,
            24.61709677419354,
            13.2,
            17.228709677419356,
            69.37161290322582,
            95.3193548387097
        ],
        [
            "06/2011",
            12.669666666666668,
            37.91,
            27.59533333333333,
            14.71,
            19.889666666666667,
            63.937999999999995,
            91.28666666666666
        ],
        [
            "07/2011",
            13.281935483870969,
            34.28,
            28.056129032258063,
            16.46,
            20.626129032258063,
            62.42516129032258,
            90.80322580645165
        ],
        [
            "08/2011",
            15.247419354838703,
            38.52,
            31.549032258064514,
            16.87,
            22.98161290322581,
            63.349032258064504,
            93.32258064516127
        ],
        [
            "09/2011",
            9.486666666666668,
            33.48,
            22.19766666666667,
            "null",
            15.151666666666667,
            57.592,
            77.58666666666666
        ],
        [
            "10/2011",
            6.909677419354839,
            31.2,
            22.41032258064516,
            7.58,
            14.131612903225804,
            74.71193548387097,
            97.44193548387096
        ],
        [
            "11/2011",
            6.477333333333334,
            20.07,
            12.338999999999999,
            "null",
            9.372000000000002,
            72.56333333333333,
            80.87000000000002
        ],
        [
            "12/2011",
            1.35,
            15.17,
            15.17,
            6.97,
            6.97,
            85.4,
            100.0
        ],
        [
            "01/2012",
            0.48322580645161284,
            15.51,
            9.115161290322579,
            -1.58,
            4.844516129032257,
            66.86774193548388,
            77.72580645161288
        ],
        [
            "02/2012",
            -1.3510344827586207,
            20.33,
            10.18793103448276,
            -2.37,
            4.139310344827586,
            66.04620689655171,
            87.2796551724138
        ],
        [
            "03/2012",
            2.302258064516129,
            26.1,
            18.260645161290324,
            5.52,
            10.224193548387095,
            66.30516129032259,
            93.10806451612903
        ],
        [
            "04/2012",
            5.040333333333334,
            23.23,
            16.041999999999998,
            6.03,
            10.199333333333334,
            76.767,
            95.50000000000001
        ],
        [
            "05/2012",
            8.638387096774194,
            37.93,
            21.137096774193548,
            "null",
            14.63967741935484,
            55.33709677419354,
            76.12903225806451
        ],
        [
            "06/2012",
            7.000666666666666,
            34.45,
            15.501666666666669,
            "null",
            11.273333333333333,
            35.933333333333344,
            51.95333333333334
        ],
        [
            "07/2012",
            13.49258064516129,
            37.78,
            28.69161290322581,
            "null",
            20.93645161290323,
            52.73322580645162,
            80.2283870967742
        ],
        [
            "08/2012",
            12.815161290322582,
            40.73,
            27.496774193548383,
            "null",
            20.02032258064516,
            49.14096774193549,
            75.98193548387098
        ],
        [
            "09/2012",
            11.236333333333333,
            33.0,
            26.471999999999998,
            11.85,
            18.55366666666667,
            68.124,
            92.92999999999996
        ],
        [
            "10/2012",
            7.913870967741936,
            30.27,
            20.876451612903228,
            5.44,
            13.643548387096773,
            80.92935483870967,
            96.61935483870967
        ],
        [
            "11/2012",
            4.452333333333333,
            21.01,
            13.849999999999996,
            3.15,
            8.76433333333333,
            83.6176666666667,
            96.32666666666665
        ],
        [
            "12/2012",
            3.7,
            11.36,
            11.36,
            6.75,
            6.75,
            90.6,
            99.9
        ],
        [
            "01/2013",
            0.25322580645161286,
            18.39,
            11.681290322580645,
            1.58,
            5.569999999999999,
            84.50387096774193,
            98.66129032258063
        ],
        [
            "02/2013",
            1.5025,
            14.85,
            9.858571428571425,
            0.11,
            5.48785714285714,
            81.45035714285716,
            96.47857142857143
        ],
        [
            "03/2013",
            2.8074193548387103,
            19.02,
            12.196451612903225,
            "null",
            7.498387096774193,
            68.92580645161291,
            84.13870967741937
        ],
        [
            "04/2013",
            5.878,
            28.14,
            17.513666666666666,
            4.64,
            11.511333333333331,
            70.14233333333333,
            91.1566666666667
        ],
        [
            "05/2013",
            6.667096774193548,
            25.32,
            17.532903225806447,
            8.39,
            11.914193548387104,
            74.61999999999998,
            93.56774193548387
        ],
        [
            "06/2013",
            11.633999999999999,
            33.22,
            24.457,
            12.78,
            17.794333333333334,
            68.47633333333334,
            91.79666666666664
        ],
        [
            "07/2013",
            16.67645161290323,
            35.84,
            32.1341935483871,
            20.59,
            24.408709677419356,
            61.91000000000002,
            91.49096774193552
        ],
        [
            "08/2013",
            14.67225806451613,
            35.51,
            29.388387096774192,
            17.82,
            21.387419354838705,
            66.81096774193549,
            91.63225806451611
        ],
        [
            "09/2013",
            12.153333333333334,
            31.29,
            26.423000000000002,
            15.11,
            18.578333333333333,
            72.63533333333335,
            95.22666666666669
        ],
        [
            "10/2013",
            9.263225806451613,
            29.2,
            21.74096774193548,
            7.87,
            15.029354838709672,
            77.47838709677418,
            95.83548387096776
        ],
        [
            "11/2013",
            4.770333333333334,
            23.3,
            12.903999999999998,
            -1.28,
            8.674333333333331,
            76.81833333333331,
            90.61
        ],
        [
            "12/2013",
            0.14,
            13.2,
            13.2,
            6.38,
            6.38,
            87.6,
            99.7
        ],
        [
            "01/2014",
            3.4106451612903217,
            16.88,
            11.461290322580645,
            1.74,
            7.275161290322581,
            84.01225806451613,
            95.66129032258067
        ],
        [
            "02/2014",
            0.7528571428571429,
            20.85,
            12.561785714285715,
            2.46,
            6.483214285714285,
            78.33857142857143,
            95.9857142857143
        ],
        [
            "03/2014",
            3.6274193548387093,
            24.93,
            16.38483870967742,
            4.03,
            9.841935483870964,
            71.45999999999998,
            92.72580645161288
        ],
        [
            "04/2014",
            7.2090000000000005,
            26.72,
            20.849,
            10.33,
            13.75366666666667,
            71.25133333333333,
            93.6253333333333
        ],
        [
            "05/2014",
            8.621935483870965,
            28.13,
            21.883870967741935,
            12.37,
            15.188387096774196,
            63.77741935483872,
            89.7709677419355
        ],
        [
            "06/2014",
            13.345666666666663,
            33.96,
            28.56533333333333,
            15.1,
            20.799000000000003,
            60.278999999999996,
            89.68466666666663
        ],
        [
            "07/2014",
            14.509032258064519,
            37.05,
            27.760645161290324,
            16.46,
            20.87096774193548,
            66.35032258064517,
            90.81064516129034
        ],
        [
            "08/2014",
            13.693225806451611,
            33.89,
            28.449677419354842,
            16.24,
            20.626774193548382,
            69.90870967741935,
            93.40967741935485
        ],
        [
            "09/2014",
            13.341,
            33.36,
            27.39633333333334,
            13.67,
            19.695333333333334,
            73.30333333333331,
            95.38999999999997
        ],
        [
            "10/2014",
            10.01967741935484,
            28.47,
            23.791935483870965,
            11.0,
            16.198387096774198,
            74.65903225806451,
            93.90967741935484
        ],
        [
            "11/2014",
            5.6049999999999995,
            20.29,
            15.264999999999999,
            6.32,
            10.204999999999997,
            85.76399999999998,
            97.61666666666669
        ],
        [
            "12/2014",
            -2.95,
            15.19,
            15.19,
            6.2,
            6.2,
            39.6,
            88.1
        ],
        [
            "01/2015",
            -0.12935483870967762,
            17.0,
            10.556129032258061,
            1.21,
            4.854516129032259,
            82.38354838709677,
            95.69999999999999
        ],
        [
            "02/2015",
            0.689642857142857,
            19.09,
            9.940714285714282,
            -0.56,
            5.0125,
            80.43428571428572,
            94.17857142857143
        ],
        [
            "03/2015",
            3.398709677419354,
            22.64,
            15.696774193548391,
            4.78,
            9.408387096774193,
            73.39483870967742,
            92.51
        ],
        [
            "04/2015",
            5.866,
            25.59,
            20.148333333333333,
            10.89,
            13.010999999999997,
            68.57633333333334,
            92.62666666666668
        ],
        [
            "05/2015",
            10.248064516129032,
            33.49,
            24.652258064516133,
            12.2,
            17.298709677419353,
            61.56451612903226,
            87.30645161290325
        ],
        [
            "06/2015",
            14.160666666666664,
            38.12,
            29.861333333333327,
            15.78,
            21.759666666666668,
            61.01066666666667,
            87.44466666666668
        ],
        [
            "07/2015",
            16.48387096774194,
            38.52,
            31.839354838709685,
            16.79,
            23.575806451612895,
            61.27612903225807,
            87.7583870967742
        ],
        [
            "08/2015",
            14.58,
            36.03,
            30.04064516129032,
            17.7,
            22.12387096774193,
            65.22258064516129,
            92.58064516129035
        ],
        [
            "09/2015",
            9.803333333333335,
            28.66,
            24.767666666666667,
            14.26,
            16.81,
            70.67999999999999,
            94.98666666666668
        ],
        [
            "10/2015",
            8.334838709677417,
            26.88,
            20.27032258064516,
            8.09,
            13.90677419354839,
            73.50193548387097,
            92.18870967741935
        ],
        [
            "11/2015",
            5.35733333333333,
            22.3,
            15.548666666666666,
            1.29,
            9.95,
            85.235,
            96.33333333333331
        ],
        [
            "12/2015",
            1.69,
            13.26,
            13.26,
            8.28,
            8.28,
            86.4,
            100.0
        ],
        [
            "01/2016",
            2.63258064516129,
            17.47,
            11.651290322580644,
            2.67,
            6.9738709677419335,
            86.52870967741936,
            97.03225806451614
        ],
        [
            "02/2016",
            1.5182758620689656,
            20.49,
            12.112068965517244,
            "null",
            6.3868965517241385,
            77.24827586206898,
            91.9896551724138
        ],
        [
            "03/2016",
            2.7429032258064527,
            23.52,
            13.156451612903227,
            "null",
            7.736774193548386,
            73.42064516129032,
            90.36774193548386
        ],
        [
            "04/2016",
            5.476333333333332,
            24.65,
            17.374333333333333,
            6.82,
            11.25866666666667,
            69.297,
            91.24666666666667
        ],
        [
            "05/2016",
            9.288709677419357,
            30.15,
            22.259354838709676,
            11.84,
            15.487096774193553,
            68.92870967741936,
            91.4451612903226
        ],
        [
            "06/2016",
            13.059666666666665,
            35.85,
            27.45233333333334,
            "null",
            19.825333333333337,
            57.54333333333333,
            84.00533333333334
        ],
        [
            "07/2016",
            15.319354838709682,
            38.47,
            30.335483870967746,
            16.35,
            22.38548387096774,
            61.11451612903225,
            87.21290322580644
        ],
        [
            "08/2016",
            14.066129032258065,
            36.31,
            31.10193548387097,
            17.6,
            22.173225806451615,
            61.49354838709678,
            89.97419354838709
        ],
        [
            "09/2016",
            12.568333333333333,
            36.58,
            27.676000000000005,
            14.22,
            19.562666666666665,
            69.03166666666668,
            93.06333333333333
        ],
        [
            "10/2016",
            8.136451612903224,
            28.66,
            21.077096774193553,
            8.53,
            14.045161290322579,
            76.32387096774193,
            95.18387096774194
        ],
        [
            "11/2016",
            3.5213333333333328,
            21.3,
            13.664666666666667,
            2.99,
            8.190666666666665,
            83.97599999999998,
            96.32333333333334
        ],
        [
            "12/2016",
            0.35,
            1.76,
            1.76,
            1.21,
            1.21,
            97.7,
            100.0
        ],
        [
            "01/2017",
            -0.6122580645161292,
            17.07,
            10.241612903225807,
            -2.44,
            4.4880645161290325,
            75.90387096774195,
            92.76451612903227
        ],
        [
            "02/2017",
            2.165,
            19.68,
            14.15285714285714,
            5.02,
            7.913571428571429,
            79.83285714285716,
            95.56785714285716
        ],
        [
            "03/2017",
            3.899032258064516,
            26.88,
            18.019032258064513,
            4.7,
            10.753870967741934,
            72.55258064516129,
            94.28387096774193
        ],
        [
            "04/2017",
            4.430666666666667,
            27.34,
            20.721999999999994,
            8.2,
            12.787000000000003,
            59.79533333333334,
            89.06099999999999
        ],
        [
            "05/2017",
            10.440967741935484,
            34.57,
            25.9641935483871,
            10.41,
            18.12838709677419,
            63.941935483870964,
            91.58838709677418
        ],
        [
            "06/2017",
            14.889,
            38.2,
            30.381666666666668,
            13.26,
            22.035999999999998,
            64.31633333333335,
            92.96666666666668
        ],
        [
            "07/2017",
            15.704193548387096,
            37.05,
            31.359354838709674,
            17.22,
            22.992258064516125,
            60.737741935483875,
            87.75548387096777
        ],
        [
            "08/2017",
            14.93483870967742,
            37.32,
            30.171935483870968,
            15.61,
            21.799999999999997,
            63.86677419354838,
            89.69677419354836
        ],
        [
            "09/2017",
            9.98633333333333,
            31.02,
            24.164999999999996,
            11.2,
            16.773,
            71.15233333333335,
            93.75333333333334
        ],
        [
            "10/2017",
            7.981935483870966,
            27.8,
            23.220000000000002,
            9.34,
            15.073225806451612,
            71.8841935483871,
            93.22580645161288
        ],
        [
            "11/2017",
            2.6793333333333327,
            21.5,
            14.33433333333333,
            1.72,
            7.963333333333334,
            74.05366666666669,
            91.47666666666666
        ],
        [
            "12/2017",
            "null",
            12.26,
            12.26,
            9.51,
            9.51,
            76.5,
            95.7
        ],
        [
            "01/2018",
            0.803225806451613,
            18.56,
            2.589354838709678,
            "null",
            1.6312903225806452,
            16.838709677419356,
            18.97741935483871
        ],
        [
            "02/2018",
            "null",
            "null",
            "null",
            "null",
            "null",
            "null",
            "null"
        ],
        [
            "03/2018",
            "null",
            "null",
            "null",
            "null",
            "null",
            "null",
            "null"
        ],
        [
            "04/2018",
            "null",
            "null",
            "null",
            "null",
            "null",
            "null",
            "null"
        ],
        [
            "05/2018",
            "null",
            "null",
            "null",
            "null",
            "null",
            "null",
            "null"
        ],
        [
            "06/2018",
            "null",
            "null",
            "null",
            "null",
            "null",
            "null",
            "null"
        ],
        [
            "07/2018",
            "null",
            "null",
            "null",
            "null",
            "null",
            "null",
            "null"
        ],
        [
            "08/2018",
            "null",
            "null",
            "null",
            "null",
            "null",
            "null",
            "null"
        ],
        [
            "09/2018",
            "null",
            "null",
            "null",
            "null",
            "null",
            "null",
            "null"
        ],
        [
            "10/2018",
            "null",
            "null",
            "null",
            "null",
            "null",
            "null",
            "null"
        ],
        [
            "11/2018",
            "null",
            "null",
            "null",
            "null",
            "null",
            "null",
            "null"
        ],
        [
            "12/2018",
            -3.69,
            15.13,
            15.13,
            4.24,
            4.24,
            79.3,
            100.0
        ],
        [
            "01/2019",
            1.0090322580645161,
            14.73,
            10.14806451612903,
            0.9,
            5.34258064516129,
            76.8183870967742,
            91.5451612903226
        ],
        [
            "02/2019",
            -0.17892857142857135,
            23.18,
            15.440357142857144,
            2.99,
            7.056071428571429,
            74.75571428571428,
            96.20714285714287
        ],
        [
            "03/2019",
            2.4677419354838714,
            25.06,
            17.309032258064523,
            7.38,
            9.845483870967742,
            64.7616129032258,
            90.77580645161291
        ],
        [
            "04/2019",
            5.358666666666666,
            24.25,
            18.148666666666667,
            7.12,
            11.755666666666666,
            67.86399999999999,
            92.48666666666668
        ],
        [
            "05/2019",
            8.321935483870966,
            31.43,
            21.22741935483871,
            9.18,
            14.820322580645161,
            64.05387096774193,
            88.10290322580646
        ],
        [
            "06/2019",
            13.342666666666668,
            42.77,
            30.098999999999993,
            12.39,
            21.708333333333332,
            52.26333333333333,
            84.2243333333333
        ],
        [
            "07/2019",
            16.479032258064517,
            39.15,
            32.30838709677419,
            18.28,
            23.96903225806451,
            56.91451612903226,
            86.47903225806452
        ],
        [
            "08/2019",
            15.177741935483871,
            36.2,
            31.12225806451613,
            18.1,
            22.57967741935484,
            63.73677419354839,
            91.33548387096774
        ],
        [
            "09/2019",
            11.718333333333334,
            31.83,
            26.315,
            15.31,
            18.424333333333337,
            69.17333333333333,
            91.51666666666664
        ],
        [
            "10/2019",
            9.30032258064516,
            28.81,
            21.643225806451614,
            8.26,
            14.970645161290319,
            75.80322580645162,
            92.4451612903226
        ],
        [
            "11/2019",
            3.313333333333334,
            20.44,
            12.853999999999996,
            3.16,
            8.058666666666666,
            85.431,
            96.91666666666669
        ],
        [
            "12/2019",
            100.0,
            1.76,
            1.76,
            0.01,
            0.01,
            99.8,
            0.2
        ],
        [
            "01/2020",
            98.20967741935482,
            19.62,
            10.135483870967741,
            -5.91,
            0.6341935483870967,
            67.50161290322579,
            1.1822580645161294
        ],
        [
            "02/2020",
            96.68275862068967,
            20.7,
            16.610689655172415,
            -3.28,
            1.7355172413793103,
            48.447931034482764,
            0.07551724137931035
        ],
        [
            "03/2020",
            94.34516129032261,
            23.72,
            15.169354838709678,
            -1.33,
            3.286129032258065,
            51.986129032258056,
            3.56483870967742
        ],
        [
            "04/2020",
            94.35333333333334,
            25.61,
            19.612333333333332,
            0.62,
            8.810666666666666,
            49.68066666666667,
            2.5743333333333336
        ],
        [
            "05/2020",
            88.00645161290322,
            32.71,
            24.602258064516125,
            "null",
            11.249032258064513,
            38.8883870967742,
            1.6483870967741936
        ],
        [
            "06/2020",
            91.14666666666669,
            34.59,
            26.160666666666668,
            7.02,
            12.913666666666668,
            38.52,
            1.8413333333333335
        ],
        [
            "07/2020",
            87.65806451612902,
            37.55,
            30.20741935483871,
            11.32,
            15.520645161290322,
            35.37387096774195,
            0.409032258064516
        ],
        [
            "08/2020",
            91.78709677419356,
            37.89,
            30.05709677419355,
            9.04,
            15.216129032258069,
            32.1941935483871,
            0.2809677419354839
        ],
        [
            "09/2020",
            89.65666666666667,
            32.91,
            25.16866666666667,
            "null",
            11.114333333333336,
            35.03333333333334,
            0.32399999999999995
        ],
        [
            "10/2020",
            86.80967741935484,
            24.92,
            16.916129032258063,
            -0.19,
            4.716451612903226,
            41.4941935483871,
            0.9393548387096772
        ],
        [
            "11/2020",
            96.97,
            22.78,
            15.25333333333333,
            -4.56,
            3.8923333333333336,
            60.38199999999998,
            0.6476666666666664
        ],
        [
            "12/2020",
            -0.66,
            8.15,
            8.15,
            3.31,
            3.31,
            84.5,
            99.8
        ],
        [
            "01/2021",
            0.5912903225806453,
            18.75,
            10.166774193548388,
            -2.82,
            5.263225806451612,
            82.22612903225806,
            96.1
        ],
        [
            "02/2021",
            5.110357142857144,
            19.1,
            14.796071428571427,
            6.32,
            9.594285714285714,
            79.49892857142856,
            93.91285714285713
        ],
        [
            "03/2021",
            3.3196774193548384,
            22.78,
            15.396129032258067,
            "null",
            9.30516129032258,
            66.62838709677418,
            86.5551612903226
        ],
        [
            "04/2021",
            5.355666666666666,
            23.85,
            17.409333333333333,
            7.12,
            11.169333333333334,
            66.91000000000001,
            91.33333333333331
        ],
        [
            "05/2021",
            7.841935483870968,
            30.7,
            21.68709677419354,
            "null",
            14.693225806451611,
            60.39032258064516,
            85.83225806451614
        ],
        [
            "06/2021",
            10.384666666666668,
            35.39,
            23.522333333333332,
            "null",
            16.727666666666664,
            51.26466666666667,
            74.70666666666666
        ],
        [
            "07/2021",
            14.515483870967742,
            38.83,
            29.305161290322577,
            16.1,
            21.950322580645167,
            59.86548387096773,
            88.28387096774195
        ],
        [
            "08/2021",
            14.704193548387094,
            40.22,
            29.907741935483873,
            18.29,
            21.91451612903226,
            63.91290322580646,
            91.00322580645162
        ],
        [
            "09/2021",
            13.154666666666666,
            33.11,
            25.783333333333335,
            14.5,
            18.86766666666667,
            76.08666666666667,
            95.75333333333332
        ],
        [
            "10/2021",
            6.2448387096774205,
            26.55,
            20.801612903225806,
            7.85,
            13.39258064516129,
            74.97935483870968,
            95.58709677419355
        ],
        [
            "11/2021",
            3.002333333333333,
            18.22,
            12.596666666666668,
            3.35,
            7.789333333333334,
            79.35699999999999,
            94.40666666666668
        ],
        [
            "12/2021",
            2.6779999999999995,
            18.69,
            9.818666666666667,
            1.31,
            5.99,
            91.85666666666665,
            98.41
        ]
    ]
}